{
	"configurations" : 
	[
		{
			"directories" : 
			[
				{
					"build" : ".",
					"hasInstallRule" : true,
					"jsonFile" : "directory-.-Release-690ecb236a1ae3422887.json",
					"minimumCMakeVersion" : 
					{
						"string" : "3.12"
					},
					"projectIndex" : 0,
					"source" : ".",
					"targetIndexes" : 
					[
						0,
						1,
						2
					]
				}
			],
			"name" : "Release",
			"projects" : 
			[
				{
					"directoryIndexes" : 
					[
						0
					],
					"name" : "sipeed_tof_ms_a010",
					"targetIndexes" : 
					[
						0,
						1,
						2
					]
				}
			],
			"targets" : 
			[
				{
					"directoryIndex" : 0,
					"id" : "publisher::@6890427a1f51a3e7e1df",
					"jsonFile" : "target-publisher-Release-5cde0f991df91aaedf5a.json",
					"name" : "publisher",
					"projectIndex" : 0
				},
				{
					"directoryIndex" : 0,
					"id" : "sipeed_tof_ms_a010_uninstall::@6890427a1f51a3e7e1df",
					"jsonFile" : "target-sipeed_tof_ms_a010_uninstall-Release-bf7903b39f1319673821.json",
					"name" : "sipeed_tof_ms_a010_uninstall",
					"projectIndex" : 0
				},
				{
					"directoryIndex" : 0,
					"id" : "uninstall::@6890427a1f51a3e7e1df",
					"jsonFile" : "target-uninstall-Release-31eed4dfcbc58eca7fbe.json",
					"name" : "uninstall",
					"projectIndex" : 0
				}
			]
		}
	],
	"kind" : "codemodel",
	"paths" : 
	{
		"build" : "/home/lya/ros2_ws/build/sipeed_tof_ms_a010",
		"source" : "/home/lya/ros2_ws/src/MaixSense_ROS/sipeed_tof_ms_a010_ros/ros2"
	},
	"version" : 
	{
		"major" : 2,
		"minor" : 3
	}
}
